{
"type": "FeatureCollection",
"crs": { "type": "name", "properties": { "name": "urn:ogc:def:crs:OGC:1.3:CRS84" } },
                                                                                
"features": [
{ "type": "Feature", "properties": { "ID": 1, "costFix ($m)": 0.0, "fixO&M ($m\/y)": 0.0, "varO&M ($\/tCO2)": 65.0, "capMax (MtCO2\/y)": 15.0, "capFctr": 1.0, "LON": -87.7659, "LAT": 38.3689, "NAME": 1, "CREDIT": 0.0, "#GenUnts": 1, "ID_1": 1, "ID_2": 1 }, "geometry": { "type": "Point", "coordinates": [ -87.7659, 38.3689 ] } }
]
}
